selenium_authenticated_proxy/__init__.py
selenium_authenticated_proxy/selenium_authenticated_proxy.py
selenium_authenticated_proxy/selenium_extension_generator.py
test/__init__.py
test/test_proxy.py
selenium_authenticated_proxy-1.1.1.dist-info/LICENSE
selenium_authenticated_proxy-1.1.1.dist-info/METADATA
selenium_authenticated_proxy-1.1.1.dist-info/WHEEL
selenium_authenticated_proxy-1.1.1.dist-info/top_level.txt
selenium_authenticated_proxy-1.1.1.dist-info/RECORD
