Metadata-Version: 2.1
Name: selenium-authenticated-proxy
Version: 1.1.1
Summary: A python package to add authenticated proxy support to selenium.
Home-page: https://github.com/bubblegumsoldier/selenium-authenticated-proxy
Author: Henry Müssemann
Author-email: hm@freezingdata.de
License: MIT
Keywords: proxy,selenium,auth,selenium
Platform: UNKNOWN
License-File: LICENSE
Requires-Dist: selenium
